webruntime/__init__.py
webruntime/__main__.py
webruntime/_browser.py
webruntime/_chrome.py
webruntime/_common.py
webruntime/_config.py
webruntime/_defaulticon.py
webruntime/_firefox.py
webruntime/_manage.py
webruntime/_ms.py
webruntime/_nw.py
webruntime/_qt.py
webruntime/_selenium.py
webruntime/util/__init__.py
webruntime/util/config.py
webruntime/util/icon.py
webruntime/util/png.py
webruntime/util/screenshot.py
webruntime/util/testing.py
webruntime-0.5.8.dist-info/LICENSE
webruntime-0.5.8.dist-info/METADATA
webruntime-0.5.8.dist-info/WHEEL
webruntime-0.5.8.dist-info/entry_points.txt
webruntime-0.5.8.dist-info/top_level.txt
webruntime-0.5.8.dist-info/RECORD
